pretix_simple_test_results/__init__.py
pretix_simple_test_results/apps.py
pretix_simple_test_results/forms.py
pretix_simple_test_results/signals.py
pretix_simple_test_results/urls.py
pretix_simple_test_results/views.py
pretix_simple_test_results/locale/de/LC_MESSAGES/django.mo
pretix_simple_test_results/locale/de/LC_MESSAGES/django.po
pretix_simple_test_results/locale/de_Informal/.gitkeep
pretix_simple_test_results/locale/de_Informal/LC_MESSAGES/django.mo
pretix_simple_test_results/locale/de_Informal/LC_MESSAGES/django.po
pretix_simple_test_results/static/pretix_simple_test_results/.gitkeep
pretix_simple_test_results/templates/pretix_simple_test_results/.gitkeep
pretix_simple_test_results/templates/pretix_simple_test_results/index.html
pretix_simple_test_results/templates/pretix_simple_test_results/send.html
pretix_simple_test_results/templates/pretix_simple_test_results/settings.html
pretix_simple_test_results-1.1.0.dist-info/LICENSE
pretix_simple_test_results-1.1.0.dist-info/METADATA
pretix_simple_test_results-1.1.0.dist-info/WHEEL
pretix_simple_test_results-1.1.0.dist-info/entry_points.txt
pretix_simple_test_results-1.1.0.dist-info/top_level.txt
pretix_simple_test_results-1.1.0.dist-info/RECORD
