Metadata-Version: 2.1
Name: pretix-simple-test-results
Version: 1.1.0
Summary: Simple test result sending
Home-page: https://github.com/pretix-unofficial/pretix-simple-test-results
Author: pretix
Author-email: support@pretix.eu
License: Apache
License-File: LICENSE
